pyTEF/__init__.py
pyTEF/_nbdev.py
pyTEF/calc.py
pyTEF/tef_core.py
pyTEF-0.1.dist-info/LICENSE
pyTEF-0.1.dist-info/METADATA
pyTEF-0.1.dist-info/WHEEL
pyTEF-0.1.dist-info/entry_points.txt
pyTEF-0.1.dist-info/top_level.txt
pyTEF-0.1.dist-info/RECORD
