Metadata-Version: 2.1
Name: pyTEF
Version: 0.1
Summary: Total Exchange Flow Framework using xarray
Home-page: https://github.com/florianboergel/pyTEF/tree/master/
Author: Florian Boergel, Marvin lorenz
Author-email: florian.boergel@io-warnemuende.de
License: Apache Software License 2.0
Keywords: pyTEF
Platform: UNKNOWN
Classifier: Development Status :: 5 - Production/Stable
Classifier: Intended Audience :: Developers
Classifier: Natural Language :: English
Classifier: Programming Language :: Python :: 3.6
Classifier: Programming Language :: Python :: 3.7
Classifier: Programming Language :: Python :: 3.8
Classifier: Programming Language :: Python :: 3.9
Classifier: License :: OSI Approved :: Apache Software License
Requires-Python: >=3.6
Requires-Dist: pip
Requires-Dist: packaging
Requires-Dist: netCDF4
Requires-Dist: xarray
Requires-Dist: matplotlib
Requires-Dist: numpy
Requires-Dist: gsw
Requires-Dist: tqdm
Provides-Extra: dev
